{"libro":
[{"ID":"1233","titolo":"Così parlò Zarathustra","prezzo":"30","npagine":"300","rilegato":"si","annopubb":"1883","collana":"i classici", "dataarc":"2001-1-16", "immagine":"null","reparto":"filosofia","editore":"adelphi","autore":"Friedrich Nietzsche"},
{"ID":"4321","titolo":"1984","prezzo":"15","npagine":"200","rilegato":"si","annopubb":"1949","collana":"Oscar moderni", "dataarc":"2005-7-30", "immagine":"null","reparto":"romanzo","editore":"Harvill Secker","autore":"George Orwell"},
{"ID":"6534","titolo":"L'isola del tesoro","prezzo":"14","npagine":"150","rilegato":"si","annopubb":"1883","collana":"classicini", "dataarc":"1998-12-11", "immagine":"null","reparto":"fumetti","editore":"Cassell","autore":"Robert Louis Stevenson"},
{"ID":"8756","titolo":"niente di nuovo sul fronte occidentale","prezzo":"10","npagine":"100","rilegato":"si","annopubb":"1929","collana":"i classici", "dataarc":"2006-4-5", "immagine":"null","reparto":"romanzo","editore":"Ullstein Verlag","autore":"Erich Maria Remarque"},
{"ID":"0983","titolo":"Dieci piccoli indiani","prezzo":"8","npagine":"70","rilegato":"no","annopubb":"1939","collana":"classici illustrati", "dataarc":"1996-3-23", "immagine":"null","reparto":"gialli","editore":"Mondadori","autore":"Agatha Christie"},
{"ID":"3628","titolo":"Se non ora, quando?","prezzo":"16","npagine":"200","rilegato":"si","annopubb":"1982","collana":"Einaudi tascabili", "dataarc":"1991-1-21","immagine":"null","reparto":"romanzo","editore":"adelphi","Einaudi":"Primo Levi"}
]}